hdext/__init__.py
hdext-0.0.1.dist-info/METADATA
hdext-0.0.1.dist-info/WHEEL
hdext-0.0.1.dist-info/top_level.txt
hdext-0.0.1.dist-info/RECORD
