Metadata-Version: 2.1
Name: hdext
Version: 0.0.1
Summary: Securing a private package.
Home-page: UNKNOWN
License: UNKNOWN
Platform: UNKNOWN
